GerenShixiangdeBenzhi/Dockerfile
GerenShixiangdeBenzhi/README.md
GerenShixiangdeBenzhi/__init__.py
GerenShixiangdeBenzhi/__main__.py
GerenShixiangdeBenzhi/file.epub
GerenShixiangdeBenzhi/index.html
GerenShixiangdeBenzhi/css/__init__.py
GerenShixiangdeBenzhi/css/annotations.css
GerenShixiangdeBenzhi/css/main.css
GerenShixiangdeBenzhi/css/normalize.css
GerenShixiangdeBenzhi/css/popup.css
GerenShixiangdeBenzhi/font/__init__.py
GerenShixiangdeBenzhi/font/fontello.eot
GerenShixiangdeBenzhi/font/fontello.svg
GerenShixiangdeBenzhi/font/fontello.ttf
GerenShixiangdeBenzhi/font/fontello.woff
GerenShixiangdeBenzhi/img/__init__.py
GerenShixiangdeBenzhi/img/annotator-glyph-sprite.png
GerenShixiangdeBenzhi/img/annotator-icon-sprite.png
GerenShixiangdeBenzhi/img/apple-touch-icon.png
GerenShixiangdeBenzhi/img/cancelfullscreen.png
GerenShixiangdeBenzhi/img/close.png
GerenShixiangdeBenzhi/img/fullscreen.png
GerenShixiangdeBenzhi/img/loader.gif
GerenShixiangdeBenzhi/img/menu-icon.png
GerenShixiangdeBenzhi/img/save.png
GerenShixiangdeBenzhi/img/saved.png
GerenShixiangdeBenzhi/img/settings-s.png
GerenShixiangdeBenzhi/img/settings.png
GerenShixiangdeBenzhi/img/star.png
GerenShixiangdeBenzhi/js/__init__.py
GerenShixiangdeBenzhi/js/epub.js
GerenShixiangdeBenzhi/js/epub.min.js
GerenShixiangdeBenzhi/js/epub.min.map
GerenShixiangdeBenzhi/js/hooks.min.js
GerenShixiangdeBenzhi/js/hooks.min.map
GerenShixiangdeBenzhi/js/reader.js
GerenShixiangdeBenzhi/js/reader.js.map
GerenShixiangdeBenzhi/js/reader.min.js
GerenShixiangdeBenzhi/js/reader.min.map
GerenShixiangdeBenzhi/js/hooks/__init__.py
GerenShixiangdeBenzhi/js/hooks/extensions/__init__.py
GerenShixiangdeBenzhi/js/hooks/extensions/highlight.js
GerenShixiangdeBenzhi/js/libs/__init__.py
GerenShixiangdeBenzhi/js/libs/jquery.min.js
GerenShixiangdeBenzhi/js/libs/localforage.min.js
GerenShixiangdeBenzhi/js/libs/screenfull.js
GerenShixiangdeBenzhi/js/libs/screenfull.min.js
GerenShixiangdeBenzhi/js/libs/zip.min.js
geren_shixiangde_benzhi-2022.10.9.1.dist-info/METADATA
geren_shixiangde_benzhi-2022.10.9.1.dist-info/WHEEL
geren_shixiangde_benzhi-2022.10.9.1.dist-info/entry_points.txt
geren_shixiangde_benzhi-2022.10.9.1.dist-info/top_level.txt
geren_shixiangde_benzhi-2022.10.9.1.dist-info/RECORD
